caillou/__init__.py
caillou/__main__.py
caillou/apps/__init__.py
caillou/apps/translator/__main__.py
caillou/apps/translator/languages.json
caillou/apps/translator/styles.tcss
caillou/config.py
caillou/translate.py
caillou-0.0.9.dist-info/LICENSE
caillou-0.0.9.dist-info/METADATA
caillou-0.0.9.dist-info/WHEEL
caillou-0.0.9.dist-info/entry_points.txt
caillou-0.0.9.dist-info/RECORD
